LICENSE.txt
README.md
setup.cfg
setup.py
big_query_testing_abc.egg-info/PKG-INFO
big_query_testing_abc.egg-info/SOURCES.txt
big_query_testing_abc.egg-info/dependency_links.txt
big_query_testing_abc.egg-info/requires.txt
big_query_testing_abc.egg-info/top_level.txt
url_code/__init__.py
url_code/main.py